dcTMD/__init__.py
dcTMD/__main__.py
dcTMD/_typing.py
dcTMD/dcTMD.py
dcTMD/io.py
dcTMD/storing.py
dcTMD/utils/__init__.py
dcTMD/utils/_bootstrapping.py
dcTMD/utils/_smoothing.py
dcTMD/utils/plotting.py
dcTMD-0.3.0.dist-info/LICENSE
dcTMD-0.3.0.dist-info/METADATA
dcTMD-0.3.0.dist-info/WHEEL
dcTMD-0.3.0.dist-info/entry_points.txt
dcTMD-0.3.0.dist-info/top_level.txt
dcTMD-0.3.0.dist-info/RECORD
