Metadata-Version: 2.1
Name: dcTMD
Version: 0.3.0
Summary: Analyse targeted molecular dynamics data with dcTMD
Home-page: https://github.com/moldyn/dcTMD
Author: taenzel, dieJaegerIn, braniii, floWneffetS
License: MIT License
Project-URL: Documentation, https://moldyn.github.io/dcTMD
Project-URL: Source Code, https://github.com/moldyn/dcTMD
Project-URL: Bug Tracker, https://github.com/moldyn/dcTMD/issues
Keywords: enhanced sampling,friction,MD analysis
Classifier: License :: OSI Approved :: MIT License
Classifier: Intended Audience :: Science/Research
Classifier: Natural Language :: English
Classifier: Programming Language :: Python :: 3
Classifier: Programming Language :: Python :: 3.8
Classifier: Programming Language :: Python :: 3.9
Classifier: Programming Language :: Python :: 3.10
Classifier: Topic :: Scientific/Engineering :: Physics
Classifier: Topic :: Scientific/Engineering :: Bio-Informatics
Classifier: Topic :: Software Development :: Libraries :: Python Modules
Requires-Python: >=3.8
License-File: LICENSE
Requires-Dist: numpy (>=1.21.0)
Requires-Dist: scikit-learn
Requires-Dist: beartype (>=0.10.4)
Requires-Dist: scipy
Requires-Dist: tqdm
Requires-Dist: click (>=7.0.0)
Requires-Dist: matplotlib (>=3.7)
Requires-Dist: typing-extensions (>=3.9.0) ; python_version < "3.9"
Provides-Extra: all
Requires-Dist: mkdocs-gen-files ; extra == 'all'
Requires-Dist: jupyter-contrib-nbextensions ; extra == 'all'
Requires-Dist: pytest-rerunfailures ; extra == 'all'
Requires-Dist: mkdocstrings ; extra == 'all'
Requires-Dist: mkdocs-material ; extra == 'all'
Requires-Dist: mkdocs-jupyter ; extra == 'all'
Requires-Dist: mkdocs-click ; extra == 'all'
Requires-Dist: pytest-cov ; extra == 'all'
Requires-Dist: mkdocs-section-index ; extra == 'all'
Requires-Dist: mkdocstrings-python ; extra == 'all'
Requires-Dist: pytest ; extra == 'all'
Requires-Dist: mkdocs-literate-nav ; extra == 'all'
Requires-Dist: flake8 ; extra == 'all'
Provides-Extra: docs
Requires-Dist: mkdocs-gen-files ; extra == 'docs'
Requires-Dist: jupyter-contrib-nbextensions ; extra == 'docs'
Requires-Dist: mkdocstrings ; extra == 'docs'
Requires-Dist: mkdocs-material ; extra == 'docs'
Requires-Dist: mkdocs-jupyter ; extra == 'docs'
Requires-Dist: mkdocs-click ; extra == 'docs'
Requires-Dist: mkdocs-section-index ; extra == 'docs'
Requires-Dist: mkdocstrings-python ; extra == 'docs'
Requires-Dist: mkdocs-literate-nav ; extra == 'docs'
Provides-Extra: testing
Requires-Dist: pytest-cov ; extra == 'testing'
Requires-Dist: pytest-rerunfailures ; extra == 'testing'
Requires-Dist: pytest ; extra == 'testing'
Requires-Dist: flake8 ; extra == 'testing'
